LICENSE
README.md
setup.cfg
setup.py
rsa_encryptor/__init__.py
rsa_encryptor/encryption.py
rsa_encryptor/keygen.py
rsa_encryptor/signature.py
rsa_encryptor.egg-info/PKG-INFO
rsa_encryptor.egg-info/SOURCES.txt
rsa_encryptor.egg-info/dependency_links.txt
rsa_encryptor.egg-info/requires.txt
rsa_encryptor.egg-info/top_level.txt