Metadata-Version: 2.1
Name: rsa-encryptor
Version: 0.1
Summary: =A minimal implemetation of asymetric encryption operations using RSA
Home-page: https://github.com/bahirhakimy/rsa_encryptor
Download-URL: https://github.com/BahirHakimy/rsa_encryptor/archive/refs/tags/v1.0.tar.gz
Author: Bahir Hakimi
Author-email: bahirhakimy2020@gmail.com
Keywords: RSA,Encryption,DigitalSignature
Classifier: Development Status :: 3 - Alpha
Classifier: Intended Audience :: Developers
Classifier: Topic :: Software Development :: Build Tools
Classifier: License :: OSI Approved :: MIT License
Classifier: Programming Language :: Python :: 3.9
License-File: LICENSE
